[
  {"timestamp": 0.0, "robot_wp": "M21", "worker1_wp": "M21", "worker2_wp": "M21", "distance_to_closest_person": 0.0},
  {"timestamp": 0.500011321, "robot_wp": "M21", "worker1_wp": "M20", "worker2_wp": "M20", "distance_to_closest_person": 0.0},
  {"timestamp": 1.000201806, "robot_wp": "M21", "worker1_wp": "M20", "worker2_wp": "M20", "distance_to_closest_person": 0.0},
  {"timestamp": 1.500282929, "robot_wp": "M20", "worker1_wp": "L20", "worker2_wp": "M21", "distance_to_closest_person": 0.0},
  {"timestamp": 2.010318366, "robot_wp": "L20", "worker1_wp": "L20", "worker2_wp": "M22", "distance_to_closest_person": 0.0090302401424001},
  {"timestamp": 2.520111269, "robot_wp": "L20", "worker1_wp": "K20", "worker2_wp": "M22", "distance_to_closest_person": 0.0609638672617299},
  {"timestamp": 3.029979291, "robot_wp": "L20", "worker1_wp": "K21", "worker2_wp": "L22", "distance_to_closest_person": 0.3262926910611174},
  {"timestamp": 3.530069417, "robot_wp": "L20", "worker1_wp": "L21", "worker2_wp": "L21", "distance_to_closest_person": 0.610826823031305},
  {"timestamp": 4.040123028, "robot_wp": "L19", "worker1_wp": "K21", "worker2_wp": "L22", "distance_to_closest_person": 0.8720291042255084},
  {"timestamp": 4.540509984, "robot_wp": "L19", "worker1_wp": "K21", "worker2_wp": "K22", "distance_to_closest_person": 1.4050872824961291},
  {"timestamp": 5.050085981, "robot_wp": "L19", "worker1_wp": "K22", "worker2_wp": "K22", "distance_to_closest_person": 1.8166718486073887},
  {"timestamp": 5.550108453, "robot_wp": "K19", "worker1_wp": "J22", "worker2_wp": "K22", "distance_to_closest_person": 2.240370582953692},
  {"timestamp": 6.060141296, "robot_wp": "K18", "worker1_wp": "I22", "worker2_wp": "K21", "distance_to_closest_person": 2.08511130442005},
  {"timestamp": 6.569999371000001, "robot_wp": "K18", "worker1_wp": "H21", "worker2_wp": "K22", "distance_to_closest_person": 2.429935096468609},
  {"timestamp": 7.0700181120000005, "robot_wp": "K18", "worker1_wp": "H21", "worker2_wp": "K22", "distance_to_closest_person": 2.769193987101125},
  {"timestamp": 7.580287389, "robot_wp": "K18", "worker1_wp": "H21", "worker2_wp": "J22", "distance_to_closest_person": 3.215211274902547},
  {"timestamp": 8.090183, "robot_wp": "K17", "worker1_wp": "H21", "worker2_wp": "I22", "distance_to_closest_person": 3.0587500198143536},
  {"timestamp": 8.599977602, "robot_wp": "K17", "worker1_wp": "H20", "worker2_wp": "I22", "distance_to_closest_person": 2.785790769158419},
  {"timestamp": 9.100034277, "robot_wp": "J17", "worker1_wp": "G20", "worker2_wp": "I22", "distance_to_closest_person": 2.5862675818678853},
  {"timestamp": 9.609964175999998, "robot_wp": "J17", "worker1_wp": "H19", "worker2_wp": "I22", "distance_to_closest_person": 2.050012544472801},
  {"timestamp": 10.110033736999998, "robot_wp": "J17", "worker1_wp": "H19", "worker2_wp": "H21", "distance_to_closest_person": 1.8231725249183763},
  {"timestamp": 10.610235402, "robot_wp": "I16", "worker1_wp": "H18", "worker2_wp": "I22", "distance_to_closest_person": 1.362059871440387},
  {"timestamp": 11.119982835999998, "robot_wp": "I16", "worker1_wp": "H18", "worker2_wp": "I22", "distance_to_closest_person": 1.138989891571102},
  {"timestamp": 11.620096270999998, "robot_wp": "I16", "worker1_wp": "H17", "worker2_wp": "I22", "distance_to_closest_person": 0.5927231597723461},
  {"timestamp": 12.120147792999996, "robot_wp": "I16", "worker1_wp": "H17", "worker2_wp": "I22", "distance_to_closest_person": 0.3463370102038203},
  {"timestamp": 12.630023648999998, "robot_wp": "H16", "worker1_wp": "H17", "worker2_wp": "I22", "distance_to_closest_person": 0.1289629608576717},
  {"timestamp": 13.140133121999998, "robot_wp": "H16", "worker1_wp": "H17", "worker2_wp": "I22", "distance_to_closest_person": 0.095829956338338},
  {"timestamp": 13.650348796999998, "robot_wp": "H16", "worker1_wp": "H17", "worker2_wp": "I22", "distance_to_closest_person": 0.1465054022813066},
  {"timestamp": 14.159990740999998, "robot_wp": "G15", "worker1_wp": "H16", "worker2_wp": "I22", "distance_to_closest_person": 0.2825697347697058},
  {"timestamp": 14.670788947999998, "robot_wp": "G15", "worker1_wp": "G16", "worker2_wp": "I22", "distance_to_closest_person": 0.3116441814013722},
  {"timestamp": 15.180042058999998, "robot_wp": "G15", "worker1_wp": "G16", "worker2_wp": "I22", "distance_to_closest_person": 0.4210906099736584},
  {"timestamp": 15.689980180999996, "robot_wp": "G15", "worker1_wp": "F16", "worker2_wp": "I22", "distance_to_closest_person": 0.5014615267032019},
  {"timestamp": 16.190156853999998, "robot_wp": "F15", "worker1_wp": "F16", "worker2_wp": "I22", "distance_to_closest_person": 0.6689492439456655},
  {"timestamp": 16.700387238999998, "robot_wp": "F15", "worker1_wp": "E16", "worker2_wp": "I22", "distance_to_closest_person": 0.8410569172651805},
  {"timestamp": 17.210304355999998, "robot_wp": "F15", "worker1_wp": "E16", "worker2_wp": "I22", "distance_to_closest_person": 1.146576286732523},
  {"timestamp": 17.720008566999997, "robot_wp": "F14", "worker1_wp": "D16", "worker2_wp": "I22", "distance_to_closest_person": 1.3504353997969454},
  {"timestamp": 18.220052165, "robot_wp": "F14", "worker1_wp": "D16", "worker2_wp": "I22", "distance_to_closest_person": 1.7109279854224495},
  {"timestamp": 18.729970843, "robot_wp": "E14", "worker1_wp": "C16", "worker2_wp": "I22", "distance_to_closest_person": 1.9098712180457564},
  {"timestamp": 19.230033763, "robot_wp": "E14", "worker1_wp": "C16", "worker2_wp": "I22", "distance_to_closest_person": 2.204226400854046},
  {"timestamp": 19.730047936, "robot_wp": "E14", "worker1_wp": "B16", "worker2_wp": "I22", "distance_to_closest_person": 2.474612333592397},
  {"timestamp": 20.240005887, "robot_wp": "E14", "worker1_wp": "B16", "worker2_wp": "I22", "distance_to_closest_person": 2.6406471690036857},
  {"timestamp": 20.750027853, "robot_wp": "E14", "worker1_wp": "A16", "worker2_wp": "I22", "distance_to_closest_person": 3.213686655039984},
  {"timestamp": 21.260149138, "robot_wp": "E14", "worker1_wp": "A16", "worker2_wp": "I22", "distance_to_closest_person": 3.2588646313420417},
  {"timestamp": 21.76997339, "robot_wp": "E14", "worker1_wp": "B16", "worker2_wp": "I22", "distance_to_closest_person": 3.065322112640854},
  {"timestamp": 22.08081941, "robot_wp": "E14", "worker1_wp": "B16", "worker2_wp": "I22", "distance_to_closest_person": 2.885067656494093}
]