[
  {"timestamp": 0.0, "robot_wp": "A9", "worker1_wp": "E4", "worker2_wp": "G4", "robot_jerk": 0.0},
  {"timestamp": 0.50890843, "robot_wp": "A9", "worker1_wp": "E4", "worker2_wp": "G4", "robot_jerk": 2.1817178182396525e-08},
  {"timestamp": 1.00914819, "robot_wp": "A9", "worker1_wp": "E5", "worker2_wp": "F4", "robot_jerk": 0.0394876953589393},
  {"timestamp": 1.518876419, "robot_wp": "B9", "worker1_wp": "E6", "worker2_wp": "F4", "robot_jerk": 2.33736220530166e-05},
  {"timestamp": 2.018895475, "robot_wp": "B9", "worker1_wp": "E6", "worker2_wp": "F5", "robot_jerk": 0.0394813735205005},
  {"timestamp": 2.518987842, "robot_wp": "B9", "worker1_wp": "E7", "worker2_wp": "F5", "robot_jerk": 4.928420090472842e-12},
  {"timestamp": 3.028879669, "robot_wp": "B9", "worker1_wp": "E7", "worker2_wp": "F6", "robot_jerk": 2.978804096364847e-12},
  {"timestamp": 3.528955905, "robot_wp": "C9", "worker1_wp": "E8", "worker2_wp": "F7", "robot_jerk": 2.2333794086228621e-13},
  {"timestamp": 4.039071692, "robot_wp": "C9", "worker1_wp": "E8", "worker2_wp": "F7", "robot_jerk": 8.576875198408201e-13},
  {"timestamp": 4.539293452, "robot_wp": "C9", "worker1_wp": "E9", "worker2_wp": "F8", "robot_jerk": 2.5964585136793923e-12},
  {"timestamp": 5.048881803, "robot_wp": "C9", "worker1_wp": "E9", "worker2_wp": "F9", "robot_jerk": 9.75868432842008e-07},
  {"timestamp": 5.549048493, "robot_wp": "D9", "worker1_wp": "D9", "worker2_wp": "F9", "robot_jerk": 0.499638261797302},
  {"timestamp": 6.058933673, "robot_wp": "D9", "worker1_wp": "E9", "worker2_wp": "F9", "robot_jerk": 0.2306410201229328},
  {"timestamp": 6.559103035000001, "robot_wp": "D9", "worker1_wp": "F9", "worker2_wp": "E9", "robot_jerk": 0.1201184093645787},
  {"timestamp": 7.059989453000001, "robot_wp": "D9", "worker1_wp": "F9", "worker2_wp": "E9", "robot_jerk": 0.0779431270609137},
  {"timestamp": 7.569150609000001, "robot_wp": "D9", "worker1_wp": "F8", "worker2_wp": "E9", "robot_jerk": 0.0799288331677419},
  {"timestamp": 8.078961642000001, "robot_wp": "D9", "worker1_wp": "F7", "worker2_wp": "E9", "robot_jerk": 11.160921605191744},
  {"timestamp": 8.579072197000002, "robot_wp": "D9", "worker1_wp": "G6", "worker2_wp": "E9", "robot_jerk": 5.1817922955306},
  {"timestamp": 9.089016690000005, "robot_wp": "E9", "worker1_wp": "G6", "worker2_wp": "E8", "robot_jerk": 6.182274501731197},
  {"timestamp": 9.589022468000003, "robot_wp": "E9", "worker1_wp": "G5", "worker2_wp": "E8", "robot_jerk": 0.7450053096727138},
  {"timestamp": 10.089086541000004, "robot_wp": "E9", "worker1_wp": "F6", "worker2_wp": "E8", "robot_jerk": 0.0623429953156157},
  {"timestamp": 10.599663846000004, "robot_wp": "E9", "worker1_wp": "F6", "worker2_wp": "E8", "robot_jerk": 0.3514533967726831},
  {"timestamp": 11.109099711000004, "robot_wp": "E9", "worker1_wp": "F7", "worker2_wp": "E9", "robot_jerk": 2.9603949926683227e-06},
  {"timestamp": 11.618861256000004, "robot_wp": "F9", "worker1_wp": "F7", "worker2_wp": "E9", "robot_jerk": 0.317601969861839},
  {"timestamp": 12.118894808000004, "robot_wp": "F9", "worker1_wp": "F8", "worker2_wp": "D9", "robot_jerk": 0.1529526782258204},
  {"timestamp": 12.619055265000004, "robot_wp": "F9", "worker1_wp": "F8", "worker2_wp": "D9", "robot_jerk": 0.1709084299014063},
  {"timestamp": 13.128907863000004, "robot_wp": "F8", "worker1_wp": "F8", "worker2_wp": "D9", "robot_jerk": 0.2398899428649756},
  {"timestamp": 13.638859374000004, "robot_wp": "F8", "worker1_wp": "F7", "worker2_wp": "C9", "robot_jerk": 0.0785237531930965},
  {"timestamp": 14.138991585000005, "robot_wp": "F8", "worker1_wp": "F7", "worker2_wp": "C9", "robot_jerk": 3.5315572376271745e-06},
  {"timestamp": 14.638996114000005, "robot_wp": "F8", "worker1_wp": "E8", "worker2_wp": "C9", "robot_jerk": 4.649603294010246},
  {"timestamp": 15.139299723000004, "robot_wp": "G7", "worker1_wp": "E8", "worker2_wp": "B9", "robot_jerk": 4.646824676089097},
  {"timestamp": 15.648857742000004, "robot_wp": "G7", "worker1_wp": "F9", "worker2_wp": "B9", "robot_jerk": 2.0040018599501794e-06},
  {"timestamp": 16.148919926000005, "robot_wp": "G7", "worker1_wp": "E9", "worker2_wp": "B9", "robot_jerk": 0.080069428702658},
  {"timestamp": 16.649916112000003, "robot_wp": "G7", "worker1_wp": "E9", "worker2_wp": "B9", "robot_jerk": 4.906476747277567e-07},
  {"timestamp": 17.159404572000003, "robot_wp": "G6", "worker1_wp": "D9", "worker2_wp": "A9", "robot_jerk": 1.1331586616481125e-05},
  {"timestamp": 17.668875250000003, "robot_wp": "G6", "worker1_wp": "D9", "worker2_wp": "B9", "robot_jerk": 0.0778434067365858},
  {"timestamp": 18.169062527, "robot_wp": "G6", "worker1_wp": "C9", "worker2_wp": "B9", "robot_jerk": 7.339213488895885e-08},
  {"timestamp": 18.669124558, "robot_wp": "G6", "worker1_wp": "C9", "worker2_wp": "B9", "robot_jerk": 0.0394902164337227},
  {"timestamp": 19.178862182, "robot_wp": "G5", "worker1_wp": "B9", "worker2_wp": "B9", "robot_jerk": 2.280980844879237},
  {"timestamp": 19.678877627, "robot_wp": "G5", "worker1_wp": "B9", "worker2_wp": "C9", "robot_jerk": 2.32533167987945},
  {"timestamp": 20.17894128, "robot_wp": "G5", "worker1_wp": "A9", "worker2_wp": "C9", "robot_jerk": 9.901143692240475e-10},
  {"timestamp": 20.678958342, "robot_wp": "G5", "worker1_wp": "B9", "worker2_wp": "C9", "robot_jerk": 4.643326271675264e-12},
  {"timestamp": 21.189084776, "robot_wp": "G4", "worker1_wp": "B9", "worker2_wp": "D9", "robot_jerk": 4.1471055089168894e-10},
  {"timestamp": 21.689188759, "robot_wp": "G4", "worker1_wp": "C9", "worker2_wp": "D9", "robot_jerk": 1.4809199129845633e-12},
  {"timestamp": 22.199396694, "robot_wp": "G4", "worker1_wp": "D9", "worker2_wp": "D9", "robot_jerk": 2.5810606685716078e-12},
  {"timestamp": 22.7092694, "robot_wp": "G4", "worker1_wp": "D9", "worker2_wp": "E10", "robot_jerk": 3.572818133814685e-12},
  {"timestamp": 23.218871773, "robot_wp": "G4", "worker1_wp": "E9", "worker2_wp": "E9", "robot_jerk": 0.0717272162161856},
  {"timestamp": 23.719073437, "robot_wp": "G4", "worker1_wp": "E9", "worker2_wp": "E9", "robot_jerk": 0.0288972363535139},
  {"timestamp": 24.219074717, "robot_wp": "G4", "worker1_wp": "E8", "worker2_wp": "F9", "robot_jerk": 0.0216816790607383},
  {"timestamp": 24.720061967, "robot_wp": "G4", "worker1_wp": "E8", "worker2_wp": "F9", "robot_jerk": 9.586542541946845e-08},
  {"timestamp": 25.000949149, "robot_wp": "G4", "worker1_wp": "E8", "worker2_wp": "F9", "robot_jerk": 0.0257300606130323}
]