[
  {"timestamp": 0.0, "robot_wp": "G19", "worker1_wp": "G18", "worker2_wp": "G19", "distance_to_closest_person": 0.0},
  {"timestamp": 0.509929253, "robot_wp": "G19", "worker1_wp": "G18", "worker2_wp": "G19", "distance_to_closest_person": 0.0},
  {"timestamp": 1.010128893, "robot_wp": "G19", "worker1_wp": "G18", "worker2_wp": "G19", "distance_to_closest_person": 0.0},
  {"timestamp": 1.510308568, "robot_wp": "G19", "worker1_wp": "G18", "worker2_wp": "G19", "distance_to_closest_person": 0.0},
  {"timestamp": 2.020247694, "robot_wp": "G18", "worker1_wp": "H18", "worker2_wp": "G19", "distance_to_closest_person": 0.0},
  {"timestamp": 2.530097609, "robot_wp": "G18", "worker1_wp": "H18", "worker2_wp": "G19", "distance_to_closest_person": 0.0},
  {"timestamp": 3.030779056, "robot_wp": "G18", "worker1_wp": "G19", "worker2_wp": "G18", "distance_to_closest_person": 0.0},
  {"timestamp": 3.539914176, "robot_wp": "G18", "worker1_wp": "G19", "worker2_wp": "G18", "distance_to_closest_person": 0.0},
  {"timestamp": 4.040319366, "robot_wp": "G17", "worker1_wp": "G18", "worker2_wp": "G18", "distance_to_closest_person": 0.0},
  {"timestamp": 4.549907168000001, "robot_wp": "G17", "worker1_wp": "G18", "worker2_wp": "G17", "distance_to_closest_person": 0.0},
  {"timestamp": 5.060032921, "robot_wp": "F17", "worker1_wp": "G18", "worker2_wp": "G16", "distance_to_closest_person": 0.0840145105775294},
  {"timestamp": 5.569971542, "robot_wp": "F17", "worker1_wp": "G17", "worker2_wp": "G16", "distance_to_closest_person": 0.2773019116666353},
  {"timestamp": 6.080047905000001, "robot_wp": "F16", "worker1_wp": "G17", "worker2_wp": "G15", "distance_to_closest_person": 0.309369951843387},
  {"timestamp": 6.5898941870000005, "robot_wp": "F16", "worker1_wp": "G16", "worker2_wp": "G14", "distance_to_closest_person": 0.211230730049476},
  {"timestamp": 7.089964556000001, "robot_wp": "F16", "worker1_wp": "G16", "worker2_wp": "G14", "distance_to_closest_person": 0.2093333044542095},
  {"timestamp": 7.599847083000001, "robot_wp": "F15", "worker1_wp": "H16", "worker2_wp": "G13", "distance_to_closest_person": 0.2250911116315733},
  {"timestamp": 8.110103485000002, "robot_wp": "F15", "worker1_wp": "G15", "worker2_wp": "G12", "distance_to_closest_person": 0.1542394922291243},
  {"timestamp": 8.620148133, "robot_wp": "F15", "worker1_wp": "H15", "worker2_wp": "G12", "distance_to_closest_person": 0.2312306815651216},
  {"timestamp": 9.129924613, "robot_wp": "F15", "worker1_wp": "G14", "worker2_wp": "G11", "distance_to_closest_person": 0.2216542639266601},
  {"timestamp": 9.639894703, "robot_wp": "F14", "worker1_wp": "G14", "worker2_wp": "G10", "distance_to_closest_person": 0.4059322729669876},
  {"timestamp": 10.140340412, "robot_wp": "F14", "worker1_wp": "G13", "worker2_wp": "G9", "distance_to_closest_person": 0.4908631605128957},
  {"timestamp": 10.649823969999998, "robot_wp": "F14", "worker1_wp": "G12", "worker2_wp": "G9", "distance_to_closest_person": 0.7891700477382693},
  {"timestamp": 11.149850937999998, "robot_wp": "F13", "worker1_wp": "G11", "worker2_wp": "G8", "distance_to_closest_person": 1.1999154315637186},
  {"timestamp": 11.649913741, "robot_wp": "F13", "worker1_wp": "G11", "worker2_wp": "G7", "distance_to_closest_person": 1.3434102641757666},
  {"timestamp": 12.159830433, "robot_wp": "F13", "worker1_wp": "G10", "worker2_wp": "G7", "distance_to_closest_person": 1.456995650972145},
  {"timestamp": 12.659854566, "robot_wp": "F13", "worker1_wp": "G10", "worker2_wp": "G6", "distance_to_closest_person": 1.6485075347188394},
  {"timestamp": 13.159935352, "robot_wp": "F12", "worker1_wp": "G9", "worker2_wp": "G6", "distance_to_closest_person": 1.816296548308096},
  {"timestamp": 13.669943226, "robot_wp": "F12", "worker1_wp": "G9", "worker2_wp": "G5", "distance_to_closest_person": 2.1251828863160998},
  {"timestamp": 14.179972847999998, "robot_wp": "F12", "worker1_wp": "G8", "worker2_wp": "G4", "distance_to_closest_person": 2.3140993429875083},
  {"timestamp": 14.680112730999998, "robot_wp": "F12", "worker1_wp": "G7", "worker2_wp": "G4", "distance_to_closest_person": 2.766525985059844},
  {"timestamp": 15.180357514999995, "robot_wp": "F11", "worker1_wp": "G7", "worker2_wp": "G4", "distance_to_closest_person": 2.865957474243486},
  {"timestamp": 15.680690412999995, "robot_wp": "F11", "worker1_wp": "G7", "worker2_wp": "G4", "distance_to_closest_person": 3.1075418969858344},
  {"timestamp": 16.189884734999996, "robot_wp": "F11", "worker1_wp": "G6", "worker2_wp": "G5", "distance_to_closest_person": 3.1701465916881126},
  {"timestamp": 16.690038693999995, "robot_wp": "F10", "worker1_wp": "G6", "worker2_wp": "G5", "distance_to_closest_person": 3.2721840087772565},
  {"timestamp": 17.200131989999996, "robot_wp": "F10", "worker1_wp": "G5", "worker2_wp": "G6", "distance_to_closest_person": 3.1605972059113183},
  {"timestamp": 17.709831715999997, "robot_wp": "F10", "worker1_wp": "G5", "worker2_wp": "G7", "distance_to_closest_person": 2.1881777940840457},
  {"timestamp": 18.209863646999995, "robot_wp": "F9", "worker1_wp": "G4", "worker2_wp": "G7", "distance_to_closest_person": 1.5274976533269498},
  {"timestamp": 18.720067697999998, "robot_wp": "F9", "worker1_wp": "G3", "worker2_wp": "G8", "distance_to_closest_person": 0.6497769645012175},
  {"timestamp": 19.229984937999998, "robot_wp": "F9", "worker1_wp": "G3", "worker2_wp": "G8", "distance_to_closest_person": 0.0},
  {"timestamp": 19.731369346999998, "robot_wp": "F9", "worker1_wp": "G4", "worker2_wp": "G9", "distance_to_closest_person": 0.0560301638490482},
  {"timestamp": 20.239978586999992, "robot_wp": "F8", "worker1_wp": "G4", "worker2_wp": "G10", "distance_to_closest_person": 0.7267200227376445},
  {"timestamp": 20.74985493899999, "robot_wp": "F8", "worker1_wp": "G5", "worker2_wp": "G11", "distance_to_closest_person": 1.5361750800563732},
  {"timestamp": 21.259833327999992, "robot_wp": "F8", "worker1_wp": "G5", "worker2_wp": "G11", "distance_to_closest_person": 1.5746848007574958},
  {"timestamp": 21.76990766199999, "robot_wp": "F7", "worker1_wp": "G6", "worker2_wp": "G12", "distance_to_closest_person": 0.9330874132558916},
  {"timestamp": 22.269926059999992, "robot_wp": "F7", "worker1_wp": "G6", "worker2_wp": "G13", "distance_to_closest_person": 0.250717291004356},
  {"timestamp": 22.769955215999996, "robot_wp": "F7", "worker1_wp": "G7", "worker2_wp": "G14", "distance_to_closest_person": 0.0},
  {"timestamp": 23.270073133999997, "robot_wp": "F7", "worker1_wp": "G7", "worker2_wp": "G14", "distance_to_closest_person": 0.0129500845377633},
  {"timestamp": 23.780160143999996, "robot_wp": "F6", "worker1_wp": "G8", "worker2_wp": "G15", "distance_to_closest_person": 0.6194964977733468},
  {"timestamp": 24.280193552999997, "robot_wp": "F6", "worker1_wp": "G8", "worker2_wp": "G16", "distance_to_closest_person": 1.2731934123141166},
  {"timestamp": 24.78990990999999, "robot_wp": "F6", "worker1_wp": "G9", "worker2_wp": "G17", "distance_to_closest_person": 2.176127532920596},
  {"timestamp": 25.30040337099999, "robot_wp": "F6", "worker1_wp": "G10", "worker2_wp": "G18", "distance_to_closest_person": 3.0260199824792},
  {"timestamp": 25.810061747999992, "robot_wp": "F5", "worker1_wp": "G11", "worker2_wp": "G18", "distance_to_closest_person": 3.980115786332404},
  {"timestamp": 26.31992521599999, "robot_wp": "F5", "worker1_wp": "G12", "worker2_wp": "G19", "distance_to_closest_person": 4.976421548082215},
  {"timestamp": 26.82052206399999, "robot_wp": "F5", "worker1_wp": "G12", "worker2_wp": "G18", "distance_to_closest_person": 5.608685116510608},
  {"timestamp": 27.329960941999992, "robot_wp": "F5", "worker1_wp": "G13", "worker2_wp": "G17", "distance_to_closest_person": 6.387629391925986},
  {"timestamp": 27.839919532999996, "robot_wp": "F4", "worker1_wp": "G13", "worker2_wp": "G17", "distance_to_closest_person": 7.127742912625064},
  {"timestamp": 28.340620459999997, "robot_wp": "F4", "worker1_wp": "G14", "worker2_wp": "G16", "distance_to_closest_person": 7.794662200948721},
  {"timestamp": 28.849854134999998, "robot_wp": "G4", "worker1_wp": "G14", "worker2_wp": "G15", "distance_to_closest_person": 8.571121168764503},
  {"timestamp": 29.349890931999997, "robot_wp": "G4", "worker1_wp": "G15", "worker2_wp": "G15", "distance_to_closest_person": 9.16972702254689},
  {"timestamp": 29.860732363999997, "robot_wp": "G3", "worker1_wp": "G15", "worker2_wp": "G14", "distance_to_closest_person": 8.827991213854583},
  {"timestamp": 30.37002517799999, "robot_wp": "G3", "worker1_wp": "G16", "worker2_wp": "G13", "distance_to_closest_person": 8.203065767302274},
  {"timestamp": 30.879840971999997, "robot_wp": "G3", "worker1_wp": "G17", "worker2_wp": "G12", "distance_to_closest_person": 7.544536583291801},
  {"timestamp": 31.180506362999992, "robot_wp": "G3", "worker1_wp": "G17", "worker2_wp": "G12", "distance_to_closest_person": 7.313689530953045}
]