[
  {"timestamp": 0.0, "robot_wp": "M5", "worker1_wp": "M5", "worker2_wp": "M15"},
  {"timestamp": 0.510090992, "robot_wp": "M5", "worker1_wp": "L5", "worker2_wp": "M15"},
  {"timestamp": 1.012884783, "robot_wp": "M5", "worker1_wp": "K5", "worker2_wp": "L15"},
  {"timestamp": 1.5221997900000002, "robot_wp": "M6", "worker1_wp": "K4", "worker2_wp": "K15"},
  {"timestamp": 2.030233126, "robot_wp": "L6", "worker1_wp": "K4", "worker2_wp": "K15"},
  {"timestamp": 2.5330740460000003, "robot_wp": "L6", "worker1_wp": "J4", "worker2_wp": "J15"},
  {"timestamp": 3.0404117040000003, "robot_wp": "L6", "worker1_wp": "I4", "worker2_wp": "J14"},
  {"timestamp": 3.5501637420000005, "robot_wp": "L7", "worker1_wp": "I4", "worker2_wp": "J14"},
  {"timestamp": 4.0600552510000005, "robot_wp": "L7", "worker1_wp": "H4", "worker2_wp": "I13"},
  {"timestamp": 4.563204666000001, "robot_wp": "L7", "worker1_wp": "H4", "worker2_wp": "I12"},
  {"timestamp": 5.070023247000001, "robot_wp": "L7", "worker1_wp": "G4", "worker2_wp": "I12"},
  {"timestamp": 5.579989358000001, "robot_wp": "L8", "worker1_wp": "F4", "worker2_wp": "I11"},
  {"timestamp": 6.0829185070000005, "robot_wp": "L8", "worker1_wp": "F4", "worker2_wp": "H11"},
  {"timestamp": 6.591661538, "robot_wp": "L8", "worker1_wp": "E3", "worker2_wp": "H11"},
  {"timestamp": 7.0999157660000005, "robot_wp": "L9", "worker1_wp": "E3", "worker2_wp": "G11"},
  {"timestamp": 7.600053705, "robot_wp": "L9", "worker1_wp": "E2", "worker2_wp": "G10"},
  {"timestamp": 8.111398130000001, "robot_wp": "L9", "worker1_wp": "E1", "worker2_wp": "G9"},
  {"timestamp": 8.620218134000002, "robot_wp": "L9", "worker1_wp": "E1", "worker2_wp": "G9"},
  {"timestamp": 9.129997550000002, "robot_wp": "K10", "worker1_wp": "E1", "worker2_wp": "F9"},
  {"timestamp": 9.632254258000003, "robot_wp": "K10", "worker1_wp": "D1", "worker2_wp": "E9"},
  {"timestamp": 10.139972037000003, "robot_wp": "K10", "worker1_wp": "D1", "worker2_wp": "D9"},
  {"timestamp": 10.649895668000005, "robot_wp": "K11", "worker1_wp": "C1", "worker2_wp": "D9"},
  {"timestamp": 11.150171678000005, "robot_wp": "K11", "worker1_wp": "C1", "worker2_wp": "D9"},
  {"timestamp": 11.659984960000005, "robot_wp": "K11", "worker1_wp": "B1", "worker2_wp": "C9"},
  {"timestamp": 12.160040770000002, "robot_wp": "K11", "worker1_wp": "B1", "worker2_wp": "C9"},
  {"timestamp": 12.670189533000002, "robot_wp": "K12", "worker1_wp": "B1", "worker2_wp": "B9"},
  {"timestamp": 13.180930516000002, "robot_wp": "K12", "worker1_wp": "A1", "worker2_wp": "B9"},
  {"timestamp": 13.689900675000002, "robot_wp": "K12", "worker1_wp": "A1", "worker2_wp": "A9"},
  {"timestamp": 14.189954258000002, "robot_wp": "J13", "worker1_wp": "B1", "worker2_wp": "A9"},
  {"timestamp": 14.699910315000002, "robot_wp": "J13", "worker1_wp": "B1", "worker2_wp": "B9"},
  {"timestamp": 15.199915620000002, "robot_wp": "J13", "worker1_wp": "C1", "worker2_wp": "B9"},
  {"timestamp": 15.699930199000002, "robot_wp": "J13", "worker1_wp": "C1", "worker2_wp": "C9"},
  {"timestamp": 16.199942231, "robot_wp": "J14", "worker1_wp": "D1", "worker2_wp": "D9"},
  {"timestamp": 16.700203099000003, "robot_wp": "J14", "worker1_wp": "D1", "worker2_wp": "D9"},
  {"timestamp": 17.210316133000003, "robot_wp": "J14", "worker1_wp": "E1", "worker2_wp": "D9"},
  {"timestamp": 17.710336393000002, "robot_wp": "I14", "worker1_wp": "E1", "worker2_wp": "E9"},
  {"timestamp": 18.219970290000003, "robot_wp": "I15", "worker1_wp": "E1", "worker2_wp": "E10"},
  {"timestamp": 18.720467862000003, "robot_wp": "I15", "worker1_wp": "E2", "worker2_wp": "F10"},
  {"timestamp": 19.230012445000003, "robot_wp": "I15", "worker1_wp": "E3", "worker2_wp": "F11"},
  {"timestamp": 19.740176850000005, "robot_wp": "I15", "worker1_wp": "E3", "worker2_wp": "F11"},
  {"timestamp": 20.250124024000005, "robot_wp": "I16", "worker1_wp": "F3", "worker2_wp": "G12"},
  {"timestamp": 20.76007467400001, "robot_wp": "I16", "worker1_wp": "F4", "worker2_wp": "G12"},
  {"timestamp": 21.270129310000005, "robot_wp": "H16", "worker1_wp": "G4", "worker2_wp": "G12"},
  {"timestamp": 21.780097841000003, "robot_wp": "H16", "worker1_wp": "G4", "worker2_wp": "H13"},
  {"timestamp": 22.289956668, "robot_wp": "H16", "worker1_wp": "G5", "worker2_wp": "I14"},
  {"timestamp": 22.790031487, "robot_wp": "H17", "worker1_wp": "G6", "worker2_wp": "I14"},
  {"timestamp": 23.29994016, "robot_wp": "H17", "worker1_wp": "G6", "worker2_wp": "I14"},
  {"timestamp": 23.729936647, "robot_wp": "H17", "worker1_wp": "G7", "worker2_wp": "I14"}
]