[
  {"timestamp": 0.0, "robot_wp": "M21", "worker1_wp": "M21", "worker2_wp": "M21"},
  {"timestamp": 0.509374393, "robot_wp": "M21", "worker1_wp": "M20", "worker2_wp": "M21"},
  {"timestamp": 1.010476142, "robot_wp": "M21", "worker1_wp": "M20", "worker2_wp": "M22"},
  {"timestamp": 1.510527427, "robot_wp": "M20", "worker1_wp": "M19", "worker2_wp": "L22"},
  {"timestamp": 2.019858115, "robot_wp": "L20", "worker1_wp": "M18", "worker2_wp": "K22"},
  {"timestamp": 2.52959703, "robot_wp": "L20", "worker1_wp": "L18", "worker2_wp": "J22"},
  {"timestamp": 3.0295989699999994, "robot_wp": "L20", "worker1_wp": "L18", "worker2_wp": "I22"},
  {"timestamp": 3.539475865, "robot_wp": "L19", "worker1_wp": "K18", "worker2_wp": "H21"},
  {"timestamp": 4.040585394, "robot_wp": "L19", "worker1_wp": "K17", "worker2_wp": "H21"},
  {"timestamp": 4.54967352, "robot_wp": "L19", "worker1_wp": "K17", "worker2_wp": "G21"},
  {"timestamp": 5.059414066, "robot_wp": "L19", "worker1_wp": "J17", "worker2_wp": "G20"},
  {"timestamp": 5.569545011, "robot_wp": "L18", "worker1_wp": "J17", "worker2_wp": "G19"},
  {"timestamp": 6.069656525, "robot_wp": "L18", "worker1_wp": "I17", "worker2_wp": "G19"},
  {"timestamp": 6.579504368, "robot_wp": "L18", "worker1_wp": "H17", "worker2_wp": "G18"},
  {"timestamp": 7.079574393000001, "robot_wp": "L18", "worker1_wp": "H17", "worker2_wp": "G17"},
  {"timestamp": 7.589489212, "robot_wp": "L17", "worker1_wp": "G17", "worker2_wp": "G17"},
  {"timestamp": 8.089630126, "robot_wp": "L17", "worker1_wp": "G16", "worker2_wp": "F16"},
  {"timestamp": 8.59942233, "robot_wp": "K17", "worker1_wp": "F16", "worker2_wp": "F16"},
  {"timestamp": 9.099520733, "robot_wp": "K17", "worker1_wp": "F15", "worker2_wp": "G15"},
  {"timestamp": 9.599666896, "robot_wp": "K17", "worker1_wp": "F15", "worker2_wp": "F15"},
  {"timestamp": 10.109375582999998, "robot_wp": "K16", "worker1_wp": "E14", "worker2_wp": "F14"},
  {"timestamp": 10.60956226, "robot_wp": "J16", "worker1_wp": "E14", "worker2_wp": "F14"},
  {"timestamp": 11.119703749, "robot_wp": "J16", "worker1_wp": "D14", "worker2_wp": "E14"},
  {"timestamp": 11.620671158, "robot_wp": "J16", "worker1_wp": "D14", "worker2_wp": "D14"},
  {"timestamp": 12.12941937, "robot_wp": "J16", "worker1_wp": "C14", "worker2_wp": "D14"},
  {"timestamp": 12.629542018, "robot_wp": "I16", "worker1_wp": "C14", "worker2_wp": "C14"},
  {"timestamp": 13.139434874, "robot_wp": "I15", "worker1_wp": "D14", "worker2_wp": "D14"},
  {"timestamp": 13.63944699, "robot_wp": "I15", "worker1_wp": "E15", "worker2_wp": "D14"},
  {"timestamp": 14.139979127, "robot_wp": "H15", "worker1_wp": "E15", "worker2_wp": "E15"},
  {"timestamp": 14.649393008, "robot_wp": "H15", "worker1_wp": "D16", "worker2_wp": "E15"},
  {"timestamp": 15.159386965, "robot_wp": "H15", "worker1_wp": "D16", "worker2_wp": "D16"},
  {"timestamp": 15.669422466, "robot_wp": "H15", "worker1_wp": "C16", "worker2_wp": "D16"},
  {"timestamp": 16.169465383000002, "robot_wp": "G15", "worker1_wp": "C16", "worker2_wp": "C16"},
  {"timestamp": 16.669886496000004, "robot_wp": "G15", "worker1_wp": "D16", "worker2_wp": "D16"},
  {"timestamp": 17.179540596000002, "robot_wp": "G15", "worker1_wp": "D16", "worker2_wp": "E16"},
  {"timestamp": 17.679570568000003, "robot_wp": "F14", "worker1_wp": "E16", "worker2_wp": "E16"},
  {"timestamp": 18.189496939, "robot_wp": "F14", "worker1_wp": "E15", "worker2_wp": "E15"},
  {"timestamp": 18.689707843, "robot_wp": "F14", "worker1_wp": "E15", "worker2_wp": "E14"},
  {"timestamp": 19.199933763, "robot_wp": "F14", "worker1_wp": "E14", "worker2_wp": "E14"},
  {"timestamp": 19.70978035, "robot_wp": "F14", "worker1_wp": "E15", "worker2_wp": "F14"},
  {"timestamp": 20.219361345, "robot_wp": "F14", "worker1_wp": "E15", "worker2_wp": "F14"},
  {"timestamp": 20.719431536, "robot_wp": "E14", "worker1_wp": "F15", "worker2_wp": "E14"},
  {"timestamp": 21.219433401, "robot_wp": "E14", "worker1_wp": "F15", "worker2_wp": "F13"},
  {"timestamp": 21.72011737, "robot_wp": "E14", "worker1_wp": "F15", "worker2_wp": "F14"},
  {"timestamp": 22.229410823, "robot_wp": "E14", "worker1_wp": "E15", "worker2_wp": "F15"},
  {"timestamp": 22.619494705, "robot_wp": "E14", "worker1_wp": "E15", "worker2_wp": "F14"}
]