[
  {"timestamp": 0.0, "robot_wp": "A9", "worker1_wp": "E1", "worker2_wp": "G20", "robot_jerk": 0.0},
  {"timestamp": 0.509869681, "robot_wp": "A9", "worker1_wp": "E1", "worker2_wp": "F20", "robot_jerk": 1.3946568824161373e-12},
  {"timestamp": 1.010265553, "robot_wp": "A9", "worker1_wp": "E2", "worker2_wp": "F19", "robot_jerk": 0.0394515437619019},
  {"timestamp": 1.521567505, "robot_wp": "B9", "worker1_wp": "E2", "worker2_wp": "F19", "robot_jerk": 0.0386100723921667},
  {"timestamp": 2.030379103, "robot_wp": "B9", "worker1_wp": "E3", "worker2_wp": "F18", "robot_jerk": 1.2500378832122647e-11},
  {"timestamp": 2.5397928160000003, "robot_wp": "B9", "worker1_wp": "E4", "worker2_wp": "F17", "robot_jerk": 1.1030712861395276e-11},
  {"timestamp": 3.0399740380000004, "robot_wp": "B9", "worker1_wp": "E4", "worker2_wp": "F17", "robot_jerk": 0.0394580864728663},
  {"timestamp": 3.5497082110000004, "robot_wp": "C9", "worker1_wp": "E5", "worker2_wp": "F16", "robot_jerk": 0.0387185825488313},
  {"timestamp": 4.049801329, "robot_wp": "C9", "worker1_wp": "E5", "worker2_wp": "F15", "robot_jerk": 3.2018494823335368e-12},
  {"timestamp": 4.549864221, "robot_wp": "C9", "worker1_wp": "E6", "worker2_wp": "F14", "robot_jerk": 9.25562293379396e-09},
  {"timestamp": 5.059965781, "robot_wp": "C9", "worker1_wp": "E6", "worker2_wp": "F14", "robot_jerk": 0.0387243165580386},
  {"timestamp": 5.569698479, "robot_wp": "D9", "worker1_wp": "E7", "worker2_wp": "F13", "robot_jerk": 0.1563284529330871},
  {"timestamp": 6.069721304, "robot_wp": "D9", "worker1_wp": "E7", "worker2_wp": "F12", "robot_jerk": 0.0813225838835116},
  {"timestamp": 6.56987794, "robot_wp": "D9", "worker1_wp": "E8", "worker2_wp": "F11", "robot_jerk": 0.0813033021134831},
  {"timestamp": 7.070123914, "robot_wp": "D9", "worker1_wp": "F8", "worker2_wp": "F11", "robot_jerk": 0.0800461630617092},
  {"timestamp": 7.579701956, "robot_wp": "E9", "worker1_wp": "E8", "worker2_wp": "F10", "robot_jerk": 0.0786061889470765},
  {"timestamp": 8.089641923, "robot_wp": "E9", "worker1_wp": "E7", "worker2_wp": "F9", "robot_jerk": 0.0785506541322385},
  {"timestamp": 8.600047859, "robot_wp": "E9", "worker1_wp": "E7", "worker2_wp": "F8", "robot_jerk": 0.3230888569073298},
  {"timestamp": 9.109696784, "robot_wp": "E8", "worker1_wp": "E8", "worker2_wp": "F8", "robot_jerk": 0.4332628489255379},
  {"timestamp": 9.609808609, "robot_wp": "E8", "worker1_wp": "F7", "worker2_wp": "E8", "robot_jerk": 0.0528134001319651},
  {"timestamp": 10.119668831, "robot_wp": "F8", "worker1_wp": "F8", "worker2_wp": "E8", "robot_jerk": 0.4747813279280054},
  {"timestamp": 10.61968488, "robot_wp": "F8", "worker1_wp": "F7", "worker2_wp": "E9", "robot_jerk": 0.2637089442711058},
  {"timestamp": 11.119717975, "robot_wp": "F8", "worker1_wp": "E7", "worker2_wp": "D9", "robot_jerk": 0.1683395118078208},
  {"timestamp": 11.629615101, "robot_wp": "F8", "worker1_wp": "E8", "worker2_wp": "D9", "robot_jerk": 0.0862566752270367},
  {"timestamp": 12.129809908, "robot_wp": "F8", "worker1_wp": "E8", "worker2_wp": "C9", "robot_jerk": 0.0879084970001067},
  {"timestamp": 12.639624261, "robot_wp": "F7", "worker1_wp": "E9", "worker2_wp": "C9", "robot_jerk": 0.1651554354196955},
  {"timestamp": 13.149651465, "robot_wp": "G7", "worker1_wp": "E10", "worker2_wp": "B9", "robot_jerk": 0.0797300634433139},
  {"timestamp": 13.649786628, "robot_wp": "G7", "worker1_wp": "E11", "worker2_wp": "A9", "robot_jerk": 0.0800438570764543},
  {"timestamp": 14.160269467, "robot_wp": "G7", "worker1_wp": "E11", "worker2_wp": "B9", "robot_jerk": 0.0776893853689857},
  {"timestamp": 14.669693881, "robot_wp": "G6", "worker1_wp": "E12", "worker2_wp": "C9", "robot_jerk": 0.003527492994357},
  {"timestamp": 15.179622533999998, "robot_wp": "G6", "worker1_wp": "E12", "worker2_wp": "C9", "robot_jerk": 0.0035234261468964},
  {"timestamp": 15.679695729, "robot_wp": "G6", "worker1_wp": "E13", "worker2_wp": "D9", "robot_jerk": 0.0394892638118864},
  {"timestamp": 16.189669188, "robot_wp": "G6", "worker1_wp": "F13", "worker2_wp": "E9", "robot_jerk": 0.0387228646929035},
  {"timestamp": 16.689748989, "robot_wp": "G5", "worker1_wp": "G13", "worker2_wp": "E8", "robot_jerk": 0.0394889684289083},
  {"timestamp": 17.189853289000002, "robot_wp": "G5", "worker1_wp": "G13", "worker2_wp": "E8", "robot_jerk": 4.4991875306601224e-13},
  {"timestamp": 17.700137702000003, "robot_wp": "G5", "worker1_wp": "H13", "worker2_wp": "F8", "robot_jerk": 1.0100987169749174e-12},
  {"timestamp": 18.209677871000004, "robot_wp": "G5", "worker1_wp": "I13", "worker2_wp": "F9", "robot_jerk": 1.885615720839354e-11},
  {"timestamp": 18.709743355000004, "robot_wp": "G4", "worker1_wp": "I13", "worker2_wp": "F10", "robot_jerk": 4.793832474865139e-12},
  {"timestamp": 19.209945328000003, "robot_wp": "G4", "worker1_wp": "J13", "worker2_wp": "F11", "robot_jerk": 5.94658050144616e-12},
  {"timestamp": 19.710242546000003, "robot_wp": "G4", "worker1_wp": "K13", "worker2_wp": "F11", "robot_jerk": 8.675133967845644e-12},
  {"timestamp": 20.219679631, "robot_wp": "G4", "worker1_wp": "L13", "worker2_wp": "F12", "robot_jerk": 1.6104103742613293e-12},
  {"timestamp": 20.719849242, "robot_wp": "G4", "worker1_wp": "L13", "worker2_wp": "F13", "robot_jerk": 0.0730799006603508},
  {"timestamp": 21.229606546000003, "robot_wp": "G4", "worker1_wp": "L13", "worker2_wp": "F13", "robot_jerk": 0.0283555622758665},
  {"timestamp": 21.739606578000004, "robot_wp": "G4", "worker1_wp": "L13", "worker2_wp": "F13", "robot_jerk": 0.0301089151697618},
  {"timestamp": 22.249667177000003, "robot_wp": "G4", "worker1_wp": "K13", "worker2_wp": "F12", "robot_jerk": 0.0112898216092951},
  {"timestamp": 22.749714803000003, "robot_wp": "G4", "worker1_wp": "J13", "worker2_wp": "F11", "robot_jerk": 0.0169406210516885},
  {"timestamp": 23.209676473, "robot_wp": "G4", "worker1_wp": "I13", "worker2_wp": "F10", "robot_jerk": 7.855353137648875e-08}
]