[
  {"timestamp": 0.0, "robot_wp": "M21", "worker1_wp": "M21", "worker2_wp": "D14", "distance_to_closest_person": 0.0},
  {"timestamp": 0.506093486, "robot_wp": "M21", "worker1_wp": "M20", "worker2_wp": "C14", "distance_to_closest_person": 0.1223453712425932},
  {"timestamp": 1.015727202, "robot_wp": "M21", "worker1_wp": "L20", "worker2_wp": "C14", "distance_to_closest_person": 0.2543402779536143},
  {"timestamp": 1.515951344, "robot_wp": "M20", "worker1_wp": "L19", "worker2_wp": "D14", "distance_to_closest_person": 0.5754784765631897},
  {"timestamp": 2.026028573, "robot_wp": "L20", "worker1_wp": "K19", "worker2_wp": "D14", "distance_to_closest_person": 0.8470944341080959},
  {"timestamp": 2.535709143, "robot_wp": "L20", "worker1_wp": "K18", "worker2_wp": "E15", "distance_to_closest_person": 1.1105946754787952},
  {"timestamp": 3.0458335739999995, "robot_wp": "L20", "worker1_wp": "K18", "worker2_wp": "E15", "distance_to_closest_person": 1.481399580305515},
  {"timestamp": 3.546106759, "robot_wp": "L19", "worker1_wp": "J17", "worker2_wp": "E15", "distance_to_closest_person": 1.865331445172688},
  {"timestamp": 4.055749281, "robot_wp": "L19", "worker1_wp": "I17", "worker2_wp": "D16", "distance_to_closest_person": 2.065956291501488},
  {"timestamp": 4.5562559, "robot_wp": "L19", "worker1_wp": "I17", "worker2_wp": "D16", "distance_to_closest_person": 2.3721225031194737},
  {"timestamp": 5.065728089, "robot_wp": "L19", "worker1_wp": "H16", "worker2_wp": "D16", "distance_to_closest_person": 2.6795165652479014},
  {"timestamp": 5.565940897, "robot_wp": "L18", "worker1_wp": "H16", "worker2_wp": "C16", "distance_to_closest_person": 3.1069442366727538},
  {"timestamp": 6.076354484, "robot_wp": "L18", "worker1_wp": "G15", "worker2_wp": "D16", "distance_to_closest_person": 3.623696893311205},
  {"timestamp": 6.585832902, "robot_wp": "L18", "worker1_wp": "G15", "worker2_wp": "D16", "distance_to_closest_person": 4.134147444054931},
  {"timestamp": 7.096804884, "robot_wp": "K18", "worker1_wp": "F14", "worker2_wp": "E16", "distance_to_closest_person": 4.436006909843912},
  {"timestamp": 7.60624435, "robot_wp": "K18", "worker1_wp": "E14", "worker2_wp": "E16", "distance_to_closest_person": 4.147802977012962},
  {"timestamp": 8.115759992, "robot_wp": "K17", "worker1_wp": "E14", "worker2_wp": "F16", "distance_to_closest_person": 3.5283852504612803},
  {"timestamp": 8.617143164, "robot_wp": "K17", "worker1_wp": "D14", "worker2_wp": "F16", "distance_to_closest_person": 2.877013644166863},
  {"timestamp": 9.12587864, "robot_wp": "J17", "worker1_wp": "D14", "worker2_wp": "G16", "distance_to_closest_person": 2.165886903472332},
  {"timestamp": 9.635678374, "robot_wp": "J17", "worker1_wp": "C14", "worker2_wp": "G16", "distance_to_closest_person": 1.7982739727518102},
  {"timestamp": 10.135891819, "robot_wp": "J17", "worker1_wp": "C14", "worker2_wp": "G17", "distance_to_closest_person": 1.455338277907662},
  {"timestamp": 10.636038139, "robot_wp": "J16", "worker1_wp": "D14", "worker2_wp": "G17", "distance_to_closest_person": 1.304226733531359},
  {"timestamp": 11.145828689, "robot_wp": "I16", "worker1_wp": "E15", "worker2_wp": "G18", "distance_to_closest_person": 1.4300227144335964},
  {"timestamp": 11.655980487, "robot_wp": "I16", "worker1_wp": "E15", "worker2_wp": "G18", "distance_to_closest_person": 1.9062597268701664},
  {"timestamp": 12.156097695, "robot_wp": "I16", "worker1_wp": "E15", "worker2_wp": "G19", "distance_to_closest_person": 1.9722666337175283},
  {"timestamp": 12.665726034000002, "robot_wp": "H16", "worker1_wp": "D16", "worker2_wp": "G18", "distance_to_closest_person": 1.7730451487809669},
  {"timestamp": 13.165761298, "robot_wp": "H16", "worker1_wp": "D16", "worker2_wp": "G18", "distance_to_closest_person": 1.3523648777409123},
  {"timestamp": 13.675692502000002, "robot_wp": "H15", "worker1_wp": "C16", "worker2_wp": "G17", "distance_to_closest_person": 0.8095758860779723},
  {"timestamp": 14.175697994000002, "robot_wp": "H15", "worker1_wp": "D16", "worker2_wp": "G16", "distance_to_closest_person": 0.2994029146440016},
  {"timestamp": 14.685684509, "robot_wp": "G15", "worker1_wp": "D16", "worker2_wp": "G16", "distance_to_closest_person": 0.1990537340774716},
  {"timestamp": 15.185963039, "robot_wp": "G15", "worker1_wp": "E16", "worker2_wp": "G16", "distance_to_closest_person": 0.0746207902730524},
  {"timestamp": 15.695905587, "robot_wp": "G15", "worker1_wp": "E16", "worker2_wp": "G16", "distance_to_closest_person": 0.0806034327309315},
  {"timestamp": 16.205900008, "robot_wp": "G15", "worker1_wp": "F16", "worker2_wp": "G16", "distance_to_closest_person": 0.1942514698377296},
  {"timestamp": 16.715704073, "robot_wp": "F15", "worker1_wp": "F16", "worker2_wp": "G16", "distance_to_closest_person": 0.3459448804763312},
  {"timestamp": 17.215828781000003, "robot_wp": "F15", "worker1_wp": "G16", "worker2_wp": "G15", "distance_to_closest_person": 0.5099587414344622},
  {"timestamp": 17.725665278, "robot_wp": "F14", "worker1_wp": "G15", "worker2_wp": "G15", "distance_to_closest_person": 0.3719040244541904},
  {"timestamp": 18.225818824, "robot_wp": "F14", "worker1_wp": "G15", "worker2_wp": "G14", "distance_to_closest_person": 0.503452878765146},
  {"timestamp": 18.725908844000003, "robot_wp": "E14", "worker1_wp": "G14", "worker2_wp": "G14", "distance_to_closest_person": 0.6326888231588104},
  {"timestamp": 19.226011738000004, "robot_wp": "E14", "worker1_wp": "G13", "worker2_wp": "G13", "distance_to_closest_person": 0.918655286283421},
  {"timestamp": 19.726197261000003, "robot_wp": "E14", "worker1_wp": "G12", "worker2_wp": "G13", "distance_to_closest_person": 1.4570575197818705},
  {"timestamp": 20.235725710000004, "robot_wp": "E14", "worker1_wp": "G12", "worker2_wp": "G12", "distance_to_closest_person": 1.7118909918136178},
  {"timestamp": 20.745740967000003, "robot_wp": "E14", "worker1_wp": "G11", "worker2_wp": "G12", "distance_to_closest_person": 2.0015313842843763},
  {"timestamp": 21.245785527, "robot_wp": "E14", "worker1_wp": "G10", "worker2_wp": "G11", "distance_to_closest_person": 2.2892497455338283},
  {"timestamp": 21.755716054000004, "robot_wp": "E14", "worker1_wp": "G9", "worker2_wp": "G11", "distance_to_closest_person": 2.630658542198422},
  {"timestamp": 22.105872018000003, "robot_wp": "E14", "worker1_wp": "G9", "worker2_wp": "G10", "distance_to_closest_person": 2.8999813630577798}
]