[
  {"timestamp": 0.0, "robot_wp": "M5", "worker1_wp": "M5", "worker2_wp": "G3"},
  {"timestamp": 0.50675466, "robot_wp": "M5", "worker1_wp": "L5", "worker2_wp": "G4"},
  {"timestamp": 1.007082304, "robot_wp": "M5", "worker1_wp": "K5", "worker2_wp": "G4"},
  {"timestamp": 1.516658663, "robot_wp": "M6", "worker1_wp": "K6", "worker2_wp": "F4"},
  {"timestamp": 2.017218994, "robot_wp": "L6", "worker1_wp": "K7", "worker2_wp": "F5"},
  {"timestamp": 2.526897988, "robot_wp": "L6", "worker1_wp": "K7", "worker2_wp": "F5"},
  {"timestamp": 3.026948055, "robot_wp": "L6", "worker1_wp": "K8", "worker2_wp": "G5"},
  {"timestamp": 3.536751356, "robot_wp": "L7", "worker1_wp": "K9", "worker2_wp": "F5"},
  {"timestamp": 4.046570395, "robot_wp": "L7", "worker1_wp": "K9", "worker2_wp": "F5"},
  {"timestamp": 4.556553976, "robot_wp": "L7", "worker1_wp": "K10", "worker2_wp": "F6"},
  {"timestamp": 5.056957379, "robot_wp": "L7", "worker1_wp": "K11", "worker2_wp": "G6"},
  {"timestamp": 5.566566824, "robot_wp": "L8", "worker1_wp": "K12", "worker2_wp": "G6"},
  {"timestamp": 6.076546512, "robot_wp": "L8", "worker1_wp": "J12", "worker2_wp": "G6"},
  {"timestamp": 6.586476043, "robot_wp": "L8", "worker1_wp": "I12", "worker2_wp": "F6"},
  {"timestamp": 7.086480905, "robot_wp": "L9", "worker1_wp": "I12", "worker2_wp": "F6"},
  {"timestamp": 7.596595548, "robot_wp": "L9", "worker1_wp": "H12", "worker2_wp": "G6"},
  {"timestamp": 8.096734008, "robot_wp": "L9", "worker1_wp": "G12", "worker2_wp": "G6"},
  {"timestamp": 8.607915817, "robot_wp": "L9", "worker1_wp": "F12", "worker2_wp": "G6"},
  {"timestamp": 9.116678205, "robot_wp": "L10", "worker1_wp": "F12", "worker2_wp": "G6"},
  {"timestamp": 9.616722398, "robot_wp": "L10", "worker1_wp": "E12", "worker2_wp": "G6"},
  {"timestamp": 10.126638413, "robot_wp": "L10", "worker1_wp": "E12", "worker2_wp": "G6"},
  {"timestamp": 10.636769275, "robot_wp": "K11", "worker1_wp": "D12", "worker2_wp": "G6"},
  {"timestamp": 11.146520072, "robot_wp": "K11", "worker1_wp": "C12", "worker2_wp": "G6"},
  {"timestamp": 11.646535927000002, "robot_wp": "K11", "worker1_wp": "C12", "worker2_wp": "G6"},
  {"timestamp": 12.146560693, "robot_wp": "K11", "worker1_wp": "B12", "worker2_wp": "G6"},
  {"timestamp": 12.656761005000002, "robot_wp": "K12", "worker1_wp": "B12", "worker2_wp": "G6"},
  {"timestamp": 13.156773766000002, "robot_wp": "K12", "worker1_wp": "A12", "worker2_wp": "G6"},
  {"timestamp": 13.666502569000002, "robot_wp": "K12", "worker1_wp": "A12", "worker2_wp": "G6"},
  {"timestamp": 14.166548114000005, "robot_wp": "K12", "worker1_wp": "B12", "worker2_wp": "G6"},
  {"timestamp": 14.667071413000002, "robot_wp": "K13", "worker1_wp": "B12", "worker2_wp": "G6"},
  {"timestamp": 15.176444063000002, "robot_wp": "J13", "worker1_wp": "C12", "worker2_wp": "G6"},
  {"timestamp": 15.676610600000002, "robot_wp": "J13", "worker1_wp": "C12", "worker2_wp": "G6"},
  {"timestamp": 16.186671562, "robot_wp": "J13", "worker1_wp": "D12", "worker2_wp": "G6"},
  {"timestamp": 16.686676543, "robot_wp": "J14", "worker1_wp": "E12", "worker2_wp": "G6"},
  {"timestamp": 17.186747542, "robot_wp": "J14", "worker1_wp": "E12", "worker2_wp": "G6"},
  {"timestamp": 17.696687737999998, "robot_wp": "J14", "worker1_wp": "F12", "worker2_wp": "G6"},
  {"timestamp": 18.206498048, "robot_wp": "I14", "worker1_wp": "F12", "worker2_wp": "G6"},
  {"timestamp": 18.70652724, "robot_wp": "I15", "worker1_wp": "G12", "worker2_wp": "G6"},
  {"timestamp": 19.216657227999995, "robot_wp": "I15", "worker1_wp": "H12", "worker2_wp": "G6"},
  {"timestamp": 19.72663795, "robot_wp": "I15", "worker1_wp": "H12", "worker2_wp": "G6"},
  {"timestamp": 20.23663176, "robot_wp": "I15", "worker1_wp": "I12", "worker2_wp": "G6"},
  {"timestamp": 20.746529898, "robot_wp": "I16", "worker1_wp": "J12", "worker2_wp": "G6"},
  {"timestamp": 21.246578557, "robot_wp": "I16", "worker1_wp": "J12", "worker2_wp": "G6"},
  {"timestamp": 21.746651687, "robot_wp": "H16", "worker1_wp": "K12", "worker2_wp": "G6"},
  {"timestamp": 22.256774122, "robot_wp": "H16", "worker1_wp": "K13", "worker2_wp": "G6"},
  {"timestamp": 22.766546678, "robot_wp": "H16", "worker1_wp": "K12", "worker2_wp": "G6"},
  {"timestamp": 23.276901274, "robot_wp": "H17", "worker1_wp": "K11", "worker2_wp": "G6"},
  {"timestamp": 23.608266858, "robot_wp": "H17", "worker1_wp": "K11", "worker2_wp": "G6"}
]